[
  {
    "id": 0,
    "imageUrl": "https://olive-hare-560073.hostingersite.com/midias/galeria/galeria10.jpg"
  },
  {
    "id": 1,
    "imageUrl": "https://olive-hare-560073.hostingersite.com/midias/galeria/galeria11.jpg"
  },
  {
    "id": 2,
    "imageUrl": "https://olive-hare-560073.hostingersite.com/midias/galeria/galeria12.jpg"
  },
  {
    "id": 3,
    "imageUrl": "https://olive-hare-560073.hostingersite.com/midias/galeria/galeria13.jpg"
  },
  {
    "id": 4,
    "imageUrl": "https://olive-hare-560073.hostingersite.com/midias/galeria/galeria14.jpg"
  },
  {
    "id": 5,
    "imageUrl": "https://olive-hare-560073.hostingersite.com/midias/galeria/galeria15.jpg"
  },
  {
    "id": 6,
    "imageUrl": "https://olive-hare-560073.hostingersite.com/midias/galeria/galeria16.jpg"
  },
  {
    "id": 7,
    "imageUrl": "https://olive-hare-560073.hostingersite.com/midias/galeria/galeria17.jpg"
  },
  {
    "id": 8,
    "imageUrl": "https://olive-hare-560073.hostingersite.com/midias/galeria/galeria18.jpg"
  },
  {
    "id": 9,
    "imageUrl": "https://olive-hare-560073.hostingersite.com/midias/galeria/galeria1.jpg"
  },
  {
    "id": 10,
    "imageUrl": "https://olive-hare-560073.hostingersite.com/midias/galeria/galeria2.jpg"
  },
  {
    "id": 11,
    "imageUrl": "https://olive-hare-560073.hostingersite.com/midias/galeria/galeria3.jpg"
  },
  {
    "id": 12,
    "imageUrl": "https://olive-hare-560073.hostingersite.com/midias/galeria/galeria4.jpg"
  },
  {
    "id": 13,
    "imageUrl": "https://olive-hare-560073.hostingersite.com/midias/galeria/galeria5.jpg"
  },
  {
    "id": 14,
    "imageUrl": "https://olive-hare-560073.hostingersite.com/midias/galeria/galeria6.jpg"
  },
  {
    "id": 15,
    "imageUrl": "https://olive-hare-560073.hostingersite.com/midias/galeria/galeria%207.jpg"
  },
  {
    "id": 16,
    "imageUrl": "https://olive-hare-560073.hostingersite.com/midias/galeria/galeria8.jpg"
  },
  {
    "id": 17,
    "imageUrl": "https://olive-hare-560073.hostingersite.com/midias/galeria/galeria9.jpg"
  }
]
